volt_llm_client-0.1.2.dist-info/licenses/LICENSE
voltllmclient/__init__.py
voltllmclient/client.py
voltllmclient/conversation.py
volt_llm_client-0.1.2.dist-info/METADATA
volt_llm_client-0.1.2.dist-info/WHEEL
volt_llm_client-0.1.2.dist-info/top_level.txt
volt_llm_client-0.1.2.dist-info/RECORD
