Metadata-Version: 2.4
Name: volt-llm-client
Version: 0.1.2
Summary: A lightweight client for local LLM APIs like Ollama or OpenWebUI
Home-page: https://github.com/stuarttempleton/volt-llm-client
Author: Voltur
License: MIT License
Project-URL: Homepage, https://github.com/stuarttempleton/volt-llm-client
Project-URL: Repository, https://github.com/stuarttempleton/volt-llm-client
Project-URL: Bug Tracker, https://github.com/stuarttempleton/volt-llm-client/issues
Keywords: logging,structured,volt
Classifier: Programming Language :: Python :: 3
Classifier: License :: OSI Approved :: MIT License
Classifier: Operating System :: OS Independent
Requires-Python: >=3.7
License-File: LICENSE
Requires-Dist: requests
Requires-Dist: volt-logger>=0.1.0
Provides-Extra: test
Requires-Dist: pytest; extra == "test"
Requires-Dist: requests; extra == "test"
Requires-Dist: pytest-mock; extra == "test"
Dynamic: author
Dynamic: home-page
Dynamic: license-file
Dynamic: requires-python
